Php7NeihePouxi/README.md
Php7NeihePouxi/__init__.py
Php7NeihePouxi/__main__.py
Php7NeihePouxi/file.epub
Php7NeihePouxi/index.html
Php7NeihePouxi/css/__init__.py
Php7NeihePouxi/css/annotations.css
Php7NeihePouxi/css/main.css
Php7NeihePouxi/css/normalize.css
Php7NeihePouxi/css/popup.css
Php7NeihePouxi/font/__init__.py
Php7NeihePouxi/font/fontello.eot
Php7NeihePouxi/font/fontello.svg
Php7NeihePouxi/font/fontello.ttf
Php7NeihePouxi/font/fontello.woff
Php7NeihePouxi/img/__init__.py
Php7NeihePouxi/img/annotator-glyph-sprite.png
Php7NeihePouxi/img/annotator-icon-sprite.png
Php7NeihePouxi/img/apple-touch-icon.png
Php7NeihePouxi/img/cancelfullscreen.png
Php7NeihePouxi/img/close.png
Php7NeihePouxi/img/fullscreen.png
Php7NeihePouxi/img/loader.gif
Php7NeihePouxi/img/menu-icon.png
Php7NeihePouxi/img/save.png
Php7NeihePouxi/img/saved.png
Php7NeihePouxi/img/settings-s.png
Php7NeihePouxi/img/settings.png
Php7NeihePouxi/img/star.png
Php7NeihePouxi/js/__init__.py
Php7NeihePouxi/js/epub.js
Php7NeihePouxi/js/epub.min.js
Php7NeihePouxi/js/epub.min.map
Php7NeihePouxi/js/hooks.min.js
Php7NeihePouxi/js/hooks.min.map
Php7NeihePouxi/js/reader.js
Php7NeihePouxi/js/reader.js.map
Php7NeihePouxi/js/reader.min.js
Php7NeihePouxi/js/reader.min.map
Php7NeihePouxi/js/hooks/__init__.py
Php7NeihePouxi/js/hooks/extensions/__init__.py
Php7NeihePouxi/js/hooks/extensions/highlight.js
Php7NeihePouxi/js/libs/__init__.py
Php7NeihePouxi/js/libs/jquery.min.js
Php7NeihePouxi/js/libs/localforage.min.js
Php7NeihePouxi/js/libs/screenfull.js
Php7NeihePouxi/js/libs/screenfull.min.js
Php7NeihePouxi/js/libs/zip.min.js
Php7NeihePouxi/js/plugins/__init__.py
Php7NeihePouxi/js/plugins/hypothesis.js
Php7NeihePouxi/js/plugins/search.js
php7_neihe_pouxi-2024.3.2.0.dist-info/METADATA
php7_neihe_pouxi-2024.3.2.0.dist-info/WHEEL
php7_neihe_pouxi-2024.3.2.0.dist-info/entry_points.txt
php7_neihe_pouxi-2024.3.2.0.dist-info/top_level.txt
php7_neihe_pouxi-2024.3.2.0.dist-info/RECORD
